gadb/__init__.py
cpfr_gadb-1.0.0.dist-info/METADATA
cpfr_gadb-1.0.0.dist-info/WHEEL
cpfr_gadb-1.0.0.dist-info/entry_points.txt
cpfr_gadb-1.0.0.dist-info/top_level.txt
cpfr_gadb-1.0.0.dist-info/RECORD
