Metadata-Version: 2.4
Name: cpfr-gadb
Version: 1.0.0
Summary: A small tool that crawls a directory for files matching certain wildcards and maintaining a CSV file with all of the files.
Author-email: Carsten Pfeffer <pfeffer.carsten@gmail.com>
Keywords: Game Asset,Asset,Game Asset DB,CSV
Requires-Python: >=3.7
Requires-Dist: pyyaml
